django_dramatiq_email/__init__.py
django_dramatiq_email/backends.py
django_dramatiq_email/tasks.py
django_dramatiq_email/utils.py
django_dramatiq_email-1.4.3.dist-info/LICENSE
django_dramatiq_email-1.4.3.dist-info/METADATA
django_dramatiq_email-1.4.3.dist-info/WHEEL
django_dramatiq_email-1.4.3.dist-info/RECORD
