Metadata-Version: 2.1
Name: django-dramatiq-email
Version: 1.4.3
Summary: A Django email backend using Dramatiq to send emails using background workers
Home-page: https://gitlab.com/sendcloud-public/django-dramatiq-email
License: MIT
Author: Tim Drijvers
Author-email: tim@sendcloud.com
Requires-Python: >=3.7,<4.0
Classifier: License :: OSI Approved :: MIT License
Classifier: Programming Language :: Python :: 3
Classifier: Programming Language :: Python :: 3.7
Classifier: Programming Language :: Python :: 3.8
Classifier: Programming Language :: Python :: 3.9
Classifier: Programming Language :: Python :: 3.10
Classifier: Programming Language :: Python :: 3.11
Classifier: Programming Language :: Python :: 3.12
Requires-Dist: django (<6.0)
Requires-Dist: django_dramatiq (>0.9,<1.0)
Requires-Dist: dramatiq (>=1.13.0,<2.0.0)
Project-URL: Repository, https://gitlab.com/sendcloud-public/django-dramatiq-email
